{
    "items":[
        {"id":"apple","name":"りんご","realQuality":1,"count":5,"isPlaceable":true,"qualityDetails":[3,2,0],"description":"甘いりんご"},
        {"id":"seed","name":"種","realQuality":1,"count":13,"isPlaceable":true,"qualityDetails":[3,2,0],"description":"甘いりんご"},
        {"id":"axe","name":"斧","realQuality":1,"count":1,"isPlaceable":false,"qualityDetails":[3,2,0],"description":"甘いりんご"},
        {"id":"pickaxe","name":"ツルハシ","realQuality":2,"count":1,"isPlaceable":false,"qualityDetails":[3,2,0],"description":"甘いりんご"},
        {"id":"fishing-rod","name":"釣り竿","realQuality":3,"count":1,"isPlaceable":false,"qualityDetails":[3,2,0],"description":"甘いりんご"}
    ]
}